pytreebuilder/__init__.py
pytreebuilder/pytreebuilder.py
pytreebuilder/utils.py
tests/__init__.py
tests/test_pytreebuilder.py
pytreebuilder-0.1.12.dist-info/LICENSE
pytreebuilder-0.1.12.dist-info/METADATA
pytreebuilder-0.1.12.dist-info/WHEEL
pytreebuilder-0.1.12.dist-info/top_level.txt
pytreebuilder-0.1.12.dist-info/RECORD
