Metadata-Version: 2.1
Name: pytreebuilder
Version: 0.1.12
Summary: A module to create project structures from a tree description text file
Home-page: https://github.com/eis-x/pytreebuilder
Author: eis-x
Author-email: eis-x@hotmail.com
Classifier: Programming Language :: Python :: 3
Classifier: License :: OSI Approved :: MIT License
Classifier: Operating System :: OS Independent
Requires-Python: >=3.6
License-File: LICENSE
